plbm_liumou_Stable/Apt.py
plbm_liumou_Stable/Cmd.py
plbm_liumou_Stable/Docker.py
plbm_liumou_Stable/Dpkg.py
plbm_liumou_Stable/File.py
plbm_liumou_Stable/IpRule.py
plbm_liumou_Stable/Iptables.py
plbm_liumou_Stable/Jurisdiction.py
plbm_liumou_Stable/LISTEN.py
plbm_liumou_Stable/NetStatus.py
plbm_liumou_Stable/Nmcli.py
plbm_liumou_Stable/OsInfo.py
plbm_liumou_Stable/Package.py
plbm_liumou_Stable/Process.py
plbm_liumou_Stable/README.md
plbm_liumou_Stable/Service.py
plbm_liumou_Stable/Source.py
plbm_liumou_Stable/Yum.py
plbm_liumou_Stable/__init__.py
plbm_liumou_Stable/base.py
plbm_liumou_Stable/eth.py
plbm_liumou_Stable/get.py
plbm_liumou_Stable/logger.py
plbm_liumou_Stable/requirements.txt
plbm_liumou_Stable/txt.log
plbm_liumou_Stable/security/__init__.py
plbm_liumou_Stable/security/firewalld.py
plbm_liumou_stable-1.4.8.dist-info/METADATA
plbm_liumou_stable-1.4.8.dist-info/WHEEL
plbm_liumou_stable-1.4.8.dist-info/licenses/LICENSE
plbm_liumou_stable-1.4.8.dist-info/RECORD
