Metadata-Version: 2.4
Name: plbm_liumou_Stable
Version: 1.4.8
Summary: 使用Python3进行编写的一个开源系统管理工具， 通过封装Linux系统都软件包管理、磁盘管理、文件管理、网络管理、安全管理、服务管理等内容从而实现快速开发的效果
Project-URL: Homepage, https://gitee.com/liumou_site/plbm
Project-URL: Bug Tracker, https://gitee.com/liumou_site/plbm/issues
Author-email: 坐公交也用券 <liumou.site@qq.com>
License-File: LICENSE
Classifier: License :: OSI Approved :: MIT License
Classifier: Operating System :: OS Independent
Classifier: Programming Language :: Python :: 3
Requires-Python: >=3.0
